{"stats":{"minecraft:picked_up":{"minecraft:sweet_berries":7,"minecraft:wheat_seeds":1,"minecraft:spruce_sapling":2,"minecraft:spruce_log":4,"minecraft:dirt":14},"minecraft:killed_by":{"minecraft:skeleton":1,"minecraft:spider":1,"minecraft:zombie":3,"minecraft:player":1},"minecraft:used":{"minecraft:sweet_berries":4},"minecraft:mined":{"minecraft:large_fern":9,"minecraft:grass":4,"minecraft:grass_block":1,"minecraft:tall_seagrass":1,"minecraft:tall_grass":1,"minecraft:sweet_berry_bush":3,"minecraft:spruce_leaves":5,"minecraft:spruce_log":4,"minecraft:fern":1},"minecraft:custom":{"minecraft:time_since_rest":2522,"minecraft:play_time":36937,"minecraft:sprint_one_cm":95754,"minecraft:damage_taken":1815,"minecraft:walk_one_cm":83649,"minecraft:deaths":7,"minecraft:sneak_time":127,"minecraft:walk_under_water_one_cm":4335,"minecraft:jump":262,"minecraft:damage_dealt":280,"minecraft:leave_game":5,"minecraft:time_since_death":2013,"minecraft:walk_on_water_one_cm":3827,"minecraft:total_world_time":36937,"minecraft:swim_one_cm":13290,"minecraft:fall_one_cm":7665,"minecraft:fly_one_cm":30661}},"DataVersion":3120}